simpliml/__init__.py
simpliml/about.py
simpliml/timeseriesforecast/__init__.py
simpliml/timeseriesforecast/dataAnalysis.py
simpliml/timeseriesforecast/dataBuild.py
simpliml/timeseriesforecast/dataModeling.py
simpliml/timeseriesforecast/modelPyTorch.py
simpliml/timeseriesforecast/modelScikitLearn.py
simpliml/timeseriesforecast/modelStatsModels.py
simpliml/timeseriesforecast/tsfCommon.py
simpliml-1.3.0.dist-info/licenses/LICENSE
tests/__init__.py
tests/test_run.py
simpliml-1.3.0.dist-info/METADATA
simpliml-1.3.0.dist-info/WHEEL
simpliml-1.3.0.dist-info/top_level.txt
simpliml-1.3.0.dist-info/RECORD
