Metadata-Version: 2.4
Name: simpliml
Version: 1.3.0
Summary: Machine Learning, Artificial Intelligence, Mathematics
Home-page: https://github.com/rajaddr/simpliml
Author: Dharmaraj D
Author-email: rajaddr@gmail.com
Project-URL: Issue Tracker, https://github.com/rajaddr/simpliml/issues
Project-URL: Changelog, https://github.com/rajaddr/simpliml/blob/master/CHANGELOG.md
Project-URL: Documentation, https://simpliml.readthedocs.io/
Project-URL: Repository, https://github.com/rajaddr/simpliml
Keywords: Supervised Learning,Neural Networks,Reinforcement Learning,Gradient Descent,TensorFlow,Probability Distributions,PCA,Convex Optimization,Transformers,Bayesian Inference,Markov Chains,GANs,SVD,Entropy,Attention Mechanism
Classifier: Development Status :: 1 - Planning
Classifier: Programming Language :: Python :: 3
Classifier: Programming Language :: Python :: 3.9
Classifier: Programming Language :: Python :: 3.10
Classifier: Programming Language :: Python :: 3.11
Classifier: Programming Language :: Python :: 3.12
Classifier: License :: OSI Approved :: MIT License
Classifier: Operating System :: OS Independent
Classifier: Topic :: Scientific/Engineering
Classifier: Topic :: Scientific/Engineering :: Artificial Intelligence
Classifier: Topic :: Scientific/Engineering :: Mathematics
Classifier: Topic :: Software Development
Classifier: Topic :: Software Development :: Libraries
Classifier: Topic :: Software Development :: Libraries :: Python Modules
Requires-Python: >=3.9,<3.13
License-File: LICENSE
Requires-Dist: pandas
Requires-Dist: scipy
Requires-Dist: scikit-learn
Requires-Dist: statsmodels
Requires-Dist: altair
Requires-Dist: matplotlib
Requires-Dist: seaborn
Requires-Dist: torch
Dynamic: author
Dynamic: author-email
Dynamic: classifier
Dynamic: description
Dynamic: description-content-type
Dynamic: home-page
Dynamic: keywords
Dynamic: license-file
Dynamic: project-url
Dynamic: requires-dist
Dynamic: requires-python
Dynamic: summary
